pulse_msal/__init__.py
pulse_msal/plugin.py
pulse_msal/py.typed
pulse_msal-0.1.5.dist-info/WHEEL
pulse_msal-0.1.5.dist-info/METADATA
pulse_msal-0.1.5.dist-info/RECORD
