Metadata-Version: 2.3
Name: pulse-msal
Version: 0.1.5
Summary: Add your description here
Author: Erwin Kuhn
Author-email: Erwin Kuhn <erwin.kuhn@protonmail.com>
Requires-Dist: redis ; extra == 'redis'
Requires-Python: >=3.12
Provides-Extra: redis
